httptestkit/__init__.py
httptestkit/cli.py
httptestkit/inspector.py
httptestkit/plugins/__init__.py
httptestkit/plugins/dnskit.py
httptestkit/plugins/headers.py
httptestkit/plugins/ipinfo.py
httptestkit/plugins/master.py
httptestkit-0.1.3.dist-info/DESCRIPTION.rst
httptestkit-0.1.3.dist-info/LICENSE.txt
httptestkit-0.1.3.dist-info/METADATA
httptestkit-0.1.3.dist-info/RECORD
httptestkit-0.1.3.dist-info/WHEEL
httptestkit-0.1.3.dist-info/entry_points.txt
httptestkit-0.1.3.dist-info/metadata.json
httptestkit-0.1.3.dist-info/top_level.txt
tests/__init__.py
