Metadata-Version: 2.0
Name: httptestkit
Version: 0.1.3
Summary: Test and gather info on a web site.
Home-page: https://xnode.co.za/software/httptestkit
Author: Paul Stevens
Author-email: no-reply@xnode.co.za
License: MIT
Platform: UNKNOWN
Classifier: Development Status :: 4 - Beta
Classifier: Programming Language :: Python
Classifier: Programming Language :: Python :: 3
Classifier: Programming Language :: Python :: 3.5
Classifier: Programming Language :: Python :: 3.6
Classifier: Environment :: Console
Classifier: Intended Audience :: Developers
Classifier: Intended Audience :: System Administrators
Classifier: License :: OSI Approved :: MIT License
Classifier: Topic :: Software Development
Classifier: Topic :: Terminals
Classifier: Topic :: Utilities
Requires-Dist: dnspython (>=1.15.0)
Requires-Dist: requests (>=2.12.5)
Requires-Dist: tldextract (>=2.2.0)
